linreglib/__init__.py
linreglib-0.12.dist-info/LICENSE.md
linreglib-0.12.dist-info/METADATA
linreglib-0.12.dist-info/WHEEL
linreglib-0.12.dist-info/top_level.txt
linreglib-0.12.dist-info/RECORD
