Metadata-Version: 2.1
Name: linreglib
Version: 0.12
Summary: A little linear regression library package
Home-page: https://github.com/anjolaolubusi/linreglib
Author: Anjolaoluwa Olubusi
Author-email: anjolaolubusi@gmail.com
License: MIT
Platform: UNKNOWN
